[
  {
    "img": "https://cdn.pixabay.com/photo/2015/10/05/22/37/blank-profile-picture-973460_640.png",
    "title": "Article 1 Title",
    "about": "Article 1 About",
    "body": "Lorem ipsum dolor sit amet, consectetur adipiscing elit, sed do eiusmod tempor incididunt ut labore et dolore magna aliqua. Donec ac odio tempor orci dapibus ultrices in iaculis nunc. Non sodales neque sodales ut etiam sit amet nisl purus. Orci eu lobortis elementum nibh tellus molestie nunc non. Ipsum dolor sit amet consectetur adipiscing. Ut porttitor leo a diam sollicitudin tempor. Amet porttitor eget dolor morbi non arcu. Ornare arcu odio ut sem nulla pharetra diam sit. Aliquet eget sit amet tellus cras adipiscing enim eu. Et molestie ac feugiat sed lectus vestibulum mattis. Non quam lacus suspendisse faucibus interdum posuere lorem ipsum. Placerat in egestas erat imperdiet sed euismod nisi. Nisl suscipit adipiscing bibendum est. Ac ut consequat semper viverra nam libero. Consectetur purus ut faucibus pulvinar elementum integer enim neque volutpat. Id aliquet risus feugiat in ante metus dictum at tempor. Nisl condimentum id venenatis a condimentum vitae. Eu feugiat pretium nibh ipsum consequat. Scelerisque eu ultrices vitae auctor eu augue ut. Purus semper eget duis at tellus. Quisque sagittis purus sit amet volutpat consequat mauris. Nullam vehicula ipsum a arcu cursus vitae congue mauris. Eget duis at tellus at urna condimentum mattis. Ut ornare lectus sit amet est placerat in. Cursus eget nunc scelerisque viverra mauris in aliquam sem. Adipiscing bibendum est ultricies integer quis auctor elit sed. Eget nunc scelerisque viverra mauris in aliquam sem. Diam donec adipiscing tristique risus nec feugiat in. Eros donec ac odio tempor orci. Quis eleifend quam adipiscing vitae proin sagittis nisl rhoncus mattis. Id consectetur purus ut faucibus pulvinar elementum. Neque gravida in fermentum et sollicitudin ac orci phasellus egestas. Et sollicitudin ac orci phasellus egestas tellus. Tincidunt eget nullam non nisi. Risus feugiat in ante metus. Laoreet sit amet cursus sit amet dictum. Scelerisque in dictum non consectetur a erat nam at.",
    "path": ""
  },
  {
    "img": "https://cdn.pixabay.com/photo/2015/10/05/22/37/blank-profile-picture-973460_640.png",
    "title": "Article 2 Title",
    "about": "Article 2 About",
    "body": "Article 2 Body Text",
    "path": ""
  },
  {
    "img": "https://cdn.pixabay.com/photo/2015/10/05/22/37/blank-profile-picture-973460_640.png",
    "title": "Article 3 Title",
    "about": "Article 3 About",
    "body": "Article 3 Body Text",
    "path": ""
  },
  {
    "img": "https://cdn.pixabay.com/photo/2015/10/05/22/37/blank-profile-picture-973460_640.png",
    "title": "Article 4 Title",
    "about": "Article 4 About",
    "body": "Article 4 Body Text",
    "path": ""
  },
  {
    "img": "https://cdn.pixabay.com/photo/2015/10/05/22/37/blank-profile-picture-973460_640.png",
    "title": "Article 5 Title",
    "about": "Article 5 About",
    "body": "Article 5 Body Text",
    "path": ""
  }
]